smart_preprocess/__init__.py
smart_preprocess/cleaner.py
smart_preprocess_asif-0.1.2.dist-info/licenses/LICENSE
smart_preprocess_asif-0.1.2.dist-info/METADATA
smart_preprocess_asif-0.1.2.dist-info/WHEEL
smart_preprocess_asif-0.1.2.dist-info/top_level.txt
smart_preprocess_asif-0.1.2.dist-info/RECORD
