Metadata-Version: 2.4
Name: smart_preprocess-asif
Version: 0.1.2
Summary: One-line smart preprocessing for ML: impute, encode, scale, and (optionally) clip outliers.
Author-email: Asif Pinjari <ap3929@nau.edu>
License: MIT
Project-URL: Homepage, https://github.com/asifpinjari/smart-preprocess
Project-URL: Issues, https://github.com/asifpinjari/smart-preprocess/issues
Keywords: machine-learning,preprocessing,data-cleaning,feature-engineering
Requires-Python: >=3.9
License-File: LICENSE
Requires-Dist: pandas>=2.0
Requires-Dist: numpy>=1.24
Requires-Dist: scikit-learn>=1.3
Dynamic: license-file
